COPYING
LICENSE
MANIFEST.in
README.rst
setup.py
django_hashlink.egg-info/PKG-INFO
django_hashlink.egg-info/SOURCES.txt
django_hashlink.egg-info/dependency_links.txt
django_hashlink.egg-info/not-zip-safe
django_hashlink.egg-info/requires.txt
django_hashlink.egg-info/top_level.txt
hashlink/__init__.py
hashlink/models.py
hashlink/urls.py
hashlink/views.py
hashlink/static/hashlink/hashlink.js
hashlink/static/hashlink/jquery.hashchange.js